{
    "Ar36": {
        "error": 0.00022152447169495294,
        "error_type": "SEM",
        "filter_outliers_dict": {
            "filter_outliers": true,
            "iterations": 1,
            "std_devs": 2
        },
        "fit": "linear",
        "value": 0.012533568726274374
    },
    "Ar37": {
        "error": 0.004029747730349549,
        "error_type": "SEM",
        "filter_outliers_dict": {
            "filter_outliers": true,
            "iterations": 1,
            "std_devs": 2
        },
        "fit": "linear",
        "value": -0.013367353608568002
    },
    "Ar38": {
        "error": 0.004100437527810958,
        "error_type": "SEM",
        "filter_outliers_dict": {
            "filter_outliers": true,
            "iterations": 1,
            "std_devs": 2
        },
        "fit": "linear",
        "value": 0.04435036681386911
    },
    "Ar39": {
        "error": 0.016695055123365984,
        "error_type": "SEM",
        "filter_outliers_dict": {
            "filter_outliers": true,
            "iterations": 1,
            "std_devs": 2
        },
        "fit": "Parabolic",
        "value": -0.041449096645747696
    },
    "Ar40": {
        "error": 0.015006470037466926,
        "error_type": "SEM",
        "filter_outliers_dict": {
            "filter_outliers": true,
            "iterations": 1,
            "std_devs": 3
        },
        "fit": "Parabolic",
        "value": 1.9522253858155465
    },
    "Ar41": {
        "error": 0.021521507570177095,
        "error_type": "SEM",
        "filter_outliers_dict": {
            "filter_outliers": true,
            "iterations": 1,
            "std_devs": 3
        },
        "fit": "average",
        "value": -0.2554262763446849
    }
}