{
    "Ar36": {
        "error": 0.00023959044432930043,
        "error_type": "SEM",
        "filter_outliers_dict": {
            "filter_outliers": true,
            "iterations": 1,
            "std_devs": 3,
            "use_iqr_filtering": false,
            "use_standard_deviation_filtering": false
        },
        "fit": "linear",
        "fn": 179,
        "include_baseline_error": true,
        "n": 180,
        "outlier_excluded": [
            0
        ],
        "reviewed": true,
        "user_excluded": [],
        "value": 0.00830737010870485
    },
    "Ar37": {
        "error": 0.004883362351727791,
        "error_type": "SEM",
        "filter_outliers_dict": {
            "filter_outliers": true,
            "iterations": 1,
            "std_devs": 3,
            "use_iqr_filtering": false,
            "use_standard_deviation_filtering": false
        },
        "fit": "linear",
        "fn": 180,
        "include_baseline_error": true,
        "n": 180,
        "outlier_excluded": [],
        "reviewed": true,
        "user_excluded": [],
        "value": -0.008263254974372691
    },
    "Ar38": {
        "error": 0.004142609816888709,
        "error_type": "SEM",
        "filter_outliers_dict": {
            "filter_outliers": true,
            "iterations": 1,
            "std_devs": 3,
            "use_iqr_filtering": false,
            "use_standard_deviation_filtering": false
        },
        "fit": "linear",
        "fn": 179,
        "include_baseline_error": true,
        "n": 180,
        "outlier_excluded": [
            178
        ],
        "reviewed": true,
        "user_excluded": [],
        "value": 0.052112752362242346
    },
    "Ar39": {
        "error": 0.019680628849327725,
        "error_type": "SEM",
        "filter_outliers_dict": {
            "filter_outliers": true,
            "iterations": 1,
            "std_devs": 3,
            "use_iqr_filtering": false,
            "use_standard_deviation_filtering": false
        },
        "fit": "parabolic",
        "fn": 180,
        "include_baseline_error": true,
        "n": 180,
        "outlier_excluded": [],
        "reviewed": true,
        "user_excluded": [],
        "value": -0.031126617656726287
    },
    "Ar40": {
        "error": 0.015862297330020113,
        "error_type": "SEM",
        "filter_outliers_dict": {
            "filter_outliers": true,
            "iterations": 1,
            "std_devs": 3,
            "use_iqr_filtering": false,
            "use_standard_deviation_filtering": false
        },
        "fit": "parabolic",
        "fn": 180,
        "include_baseline_error": true,
        "n": 180,
        "outlier_excluded": [],
        "reviewed": true,
        "user_excluded": [],
        "value": 0.7500796665246767
    },
    "Ar41": {
        "error": 0.022551757790590078,
        "error_type": "SEM",
        "filter_outliers_dict": {
            "filter_outliers": true,
            "iterations": 1,
            "std_devs": 3
        },
        "fit": "average",
        "value": -0.18457386361880235
    }
}